inaSpeechSegmenter_api_models/__init__.py
inaSpeechSegmenter_api_models/get_segments_request.py
inaSpeechSegmenter_api_models/get_segments_response.py
inaSpeechSegmenter_api_models/request_base.py
inaSpeechSegmenter_api_models/segment_item.py
inaSpeechSegmenter_api_models-0.1.3.dist-info/LICENSE
inaSpeechSegmenter_api_models-0.1.3.dist-info/METADATA
inaSpeechSegmenter_api_models-0.1.3.dist-info/WHEEL
inaSpeechSegmenter_api_models-0.1.3.dist-info/top_level.txt
inaSpeechSegmenter_api_models-0.1.3.dist-info/RECORD
