Metadata-Version: 2.1
Name: inaSpeechSegmenter-api-models
Version: 0.1.3
Summary: Common dependency for inaSpeechSegmenter API and client.
Home-page: https://github.com/Danand/inaSpeechSegmenter-api-models/
Download-URL: http://pypi.python.org/pypi/inaSpeechSegmenter-api-models/
Author: Andrey Danilov
Author-email: danand@inbox.ru
License: MIT
Keywords: speech-segmentation,audio-analysis,music-detection,noise-detection,speech-detection,speech-music,gender-classification,gender-representation,speaker-gender,speech,music,noise,gender,voice-activity-detection,speech-activity-detection
Platform: Platform Independent
Classifier: Development Status :: 2 - Pre-Alpha
Classifier: Intended Audience :: Developers
Classifier: License :: OSI Approved :: MIT License
Classifier: Natural Language :: English
Classifier: Operating System :: OS Independent
Classifier: Topic :: Software Development :: Libraries :: Python Modules
Classifier: Programming Language :: Python
Classifier: Programming Language :: Python :: 3.10
License-File: LICENSE
Requires-Dist: pydantic==2.10.4
